README.md
setup.py
giftsnackinifinity2/__init__.py
giftsnackinifinity2/carrello.py
giftsnackinifinity2/upload_affiliate_help8.py
giftsnackinifinity2.egg-info/PKG-INFO
giftsnackinifinity2.egg-info/SOURCES.txt
giftsnackinifinity2.egg-info/dependency_links.txt
giftsnackinifinity2.egg-info/top_level.txt
giftsnackinifinity2/mod_a/__init__.py
giftsnackinifinity2/mod_a/file_a.py
giftsnackinifinity2/mod_b/__init__.py
giftsnackinifinity2/mod_b/file_b.py