Metadata-Version: 2.1
Name: giftsnackinifinity2
Version: 1.0.0
Summary: UNKNOWN
Home-page: https://github.com/bfonfa/giftsnackinifinity2
Author: bfonfa
Author-email: bfonfa@icloud.com
License: MIT
Project-URL: Documentation, https://giftsnackinifinity2.readthedocs.io
Project-URL: Source, https://github.com/bfonfa/giftsnackinifinity2
Platform: UNKNOWN
Classifier: Development Status :: 5 - Production/Stable
Classifier: Intended Audience :: Developers
Classifier: Natural Language :: English
Classifier: License :: OSI Approved :: MIT License
